{
  "nodes": [
    {
      "url": "http://www.w3.org/mid/09147104-5C3E-410A-B37B-3202C82A78A9@jenitennison.com", 
      "replyTo": "http://www.w3.org/mid/CAGnGFMLFJTLd4wFP_mGtev3RU4vva2=MpMHdqy14f7WMGSS=NA@mail.gmail.com", 
      "from": "jeni@jenitennison.com", 
      "subject": "Re: NIR SIDETRACK Re: Change Proposal for HttpRange-14"
    }, 
    {
      "url": "http://www.w3.org/mid/094D59EA-AAB2-4063-A0AC-2EA56C299DE8@jenitennison.com", 
      "replyTo": "http://www.w3.org/mid/CAJtGsrhZ1yWMKUYbmWgszXTSfG65-y0vb9vP=KPDW_qJYGjGig@mail.gmail.com", 
      "from": "jeni@jenitennison.com", 
      "subject": "Re: Change Proposal for HttpRange-14"
    }, 
    {
      "url": "http://www.w3.org/mid/1332530598.4931.11.camel@james-laptop", 
      "replyTo": "http://www.w3.org/mid/EMEW3|08aaed167912ed465e0acb6f68e7a515o2MGCC02hg|ecs.soton.ac.uk|E6F19F02-55F0-4A9F-94C3-43236EFEEBBA@ecs.soton.ac.uk", 
      "from": "james@3roundstones.com", 
      "subject": "Re: Change Proposal for HttpRange-14"
    }, 
    {
      "url": "http://www.w3.org/mid/1332534274.1862.5.camel@james-laptop", 
      "replyTo": "http://www.w3.org/mid/66C5E682-B165-4233-A51B-32F1D0E69DAB@jenitennison.com", 
      "from": "james@3roundstones.com", 
      "subject": "Re: Change Proposal for HttpRange-14"
    }, 
    {
      "url": "http://www.w3.org/mid/1332549492.1843.27.camel@james-laptop", 
      "replyTo": "http://www.w3.org/mid/D8CF4CC8-8D2F-47D3-AD56-DE5D01724C06@jenitennison.com", 
      "from": "james@3roundstones.com", 
      "subject": "Re: Change Proposal for HttpRange-14"
    }, 
    {
      "url": "http://www.w3.org/mid/1332592732.1912.1.camel@james-laptop", 
      "replyTo": "http://www.w3.org/mid/E8814EA7-FF59-4EEE-BF4A-4F72DAF65FC6@jenitennison.com", 
      "from": "james@3roundstones.com", 
      "subject": "Re: Change Proposal for HttpRange-14"
    }, 
    {
      "url": "http://www.w3.org/mid/1332610564.1830.6.camel@james-laptop", 
      "replyTo": "http://www.w3.org/mid/DAE0EB3C-0EC0-45C3-8281-6B398051EFEF@jenitennison.com", 
      "from": "james@3roundstones.com", 
      "subject": "Re: Change Proposal for HttpRange-14"
    }, 
    {
      "url": "http://www.w3.org/mid/1332696777.2181.33496.camel@dbooth-laptop", 
      "replyTo": "http://www.w3.org/mid/3858D2E6-4CA5-4537-9D8B-B915CFE9366A@w3.org", 
      "from": "david@dbooth.org", 
      "subject": "Re: Change Proposal for HttpRange-14"
    }, 
    {
      "url": "http://www.w3.org/mid/1333041773.2181.78086.camel@dbooth-laptop", 
      "replyTo": "http://www.w3.org/mid/B5C1F24E-D304-4160-903D-F8C07C1EE648@astro.gla.ac.uk", 
      "from": "david@dbooth.org", 
      "subject": "Re: NIR SIDETRACK Re: Change Proposal for HttpRange-14"
    }, 
    {
      "url": "http://www.w3.org/mid/1333074023.2181.84542.camel@dbooth-laptop", 
      "replyTo": "http://www.w3.org/mid/CAGnGFMLFJTLd4wFP_mGtev3RU4vva2=MpMHdqy14f7WMGSS=NA@mail.gmail.com", 
      "from": "david@dbooth.org", 
      "subject": "Re: NIR SIDETRACK Re: Change Proposal for HttpRange-14"
    }, 
    {
      "url": "http://www.w3.org/mid/1333297970.2181.99703.camel@dbooth-laptop", 
      "replyTo": "http://www.w3.org/mid/20120401083544.GA9331@netestate.de", 
      "from": "david@dbooth.org", 
      "subject": "Re: NIR SIDETRACK Re: Change Proposal for HttpRange-14"
    }, 
    {
      "url": "http://www.w3.org/mid/1333330978.2181.103785.camel@dbooth-laptop", 
      "replyTo": "http://www.w3.org/mid/CAGnGFM+Uebq-556KOq+P4zEVxM=fnK+0eUnr+u1GNjT6u5X-NQ@mail.gmail.com", 
      "from": "david@dbooth.org", 
      "subject": "Re: NIR SIDETRACK Re: Change Proposal for HttpRange-14"
    }, 
    {
      "url": "http://www.w3.org/mid/1D15BB62-203F-4EB3-B814-A877A84104D4@jenitennison.com", 
      "replyTo": "http://www.w3.org/mid/CAGnGFMJWxpDbYPzUqfacaNp5eAr0Wi3DDqjLm2OSzcCuWSG0fg@mail.gmail.com", 
      "from": "jeni@jenitennison.com", 
      "subject": "Re: NIR SIDETRACK Re: Change Proposal for HttpRange-14"
    }, 
    {
      "url": "http://www.w3.org/mid/20120324154658.GA15184@netestate.de", 
      "replyTo": "http://www.w3.org/mid/4F6C8FCE.8020708@gmail.com", 
      "from": "brunni@netestate.de", 
      "subject": "Re: Change Proposal for HttpRange-14"
    }, 
    {
      "url": "http://www.w3.org/mid/20120324215926.GA24475@netestate.de", 
      "replyTo": "http://www.w3.org/mid/4F8D1C70-E67E-4A11-A144-B69DD17B5ECD@jenitennison.com", 
      "from": "brunni@netestate.de", 
      "subject": "Re: Change Proposal for HttpRange-14"
    }, 
    {
      "url": "http://www.w3.org/mid/20120324231646.GA26121@netestate.de", 
      "replyTo": "http://www.w3.org/mid/E4216A5B-5E9E-4433-9FC3-594B3A395894@jenitennison.com", 
      "from": "brunni@netestate.de", 
      "subject": "Re: Change Proposal for HttpRange-14"
    }, 
    {
      "url": "http://www.w3.org/mid/20120325001257.GA28335@netestate.de", 
      "replyTo": "http://www.w3.org/mid/20120324231646.GA26121@netestate.de", 
      "from": "brunni@netestate.de", 
      "subject": "Re: Change Proposal for HttpRange-14"
    }, 
    {
      "url": "http://www.w3.org/mid/20120325100359.GA9806@netestate.de", 
      "replyTo": "http://www.w3.org/mid/CBABFE77-7CBF-4D0F-83DD-7422ED04D588@jenitennison.com", 
      "from": "brunni@netestate.de", 
      "subject": "Re: Change Proposal for HttpRange-14"
    }, 
    {
      "url": "http://www.w3.org/mid/20120325131938.GA14318@netestate.de", 
      "replyTo": "http://www.w3.org/mid/9D86B03C-586A-4C43-BABD-277B5C2E4CCB@jenitennison.com", 
      "from": "brunni@netestate.de", 
      "subject": "Re: Change Proposal for HttpRange-14"
    }, 
    {
      "url": "http://www.w3.org/mid/20120327115202.GA22395@netestate.de", 
      "replyTo": "http://www.w3.org/mid/91DA9A68-C960-4917-B1A5-A3C93D92E34E@w3.org", 
      "from": "brunni@netestate.de", 
      "subject": "Re: NIR SIDETRACK Re: Change Proposal for HttpRange-14"
    }, 
    {
      "url": "http://www.w3.org/mid/20120327143732.GA26477@netestate.de", 
      "replyTo": "http://www.w3.org/mid/CAGnGFMJV0oz-H6+UCJpvjBy8FHWy9Di-tRVcLnU8ZP1=3xUx4w@mail.gmail.com", 
      "from": "brunni@netestate.de", 
      "subject": "Re: NIR SIDETRACK Re: Change Proposal for HttpRange-14"
    }, 
    {
      "url": "http://www.w3.org/mid/20120328185604.GA6377@netestate.de", 
      "replyTo": "http://www.w3.org/mid/4F251EA9-5349-41F8-B6CA-53420845EE31@astro.gla.ac.uk", 
      "from": "brunni@netestate.de", 
      "subject": "Re: NIR SIDETRACK Re: Change Proposal for HttpRange-14"
    }, 
    {
      "url": "http://www.w3.org/mid/20120328213504.GA10598@netestate.de", 
      "replyTo": "http://www.w3.org/mid/20120328185604.GA6377@netestate.de", 
      "from": "brunni@netestate.de", 
      "subject": "Re: NIR SIDETRACK Re: Change Proposal for HttpRange-14"
    }, 
    {
      "url": "http://www.w3.org/mid/20120331120557.GA9772@netestate.de", 
      "replyTo": "http://www.w3.org/mid/20120328213504.GA10598@netestate.de", 
      "from": "brunni@netestate.de", 
      "subject": "Re: NIR SIDETRACK Re: Change Proposal for HttpRange-14"
    }, 
    {
      "url": "http://www.w3.org/mid/20120331155303.GA15897@netestate.de", 
      "replyTo": "http://www.w3.org/mid/CAGnGFM+Uebq-556KOq+P4zEVxM=fnK+0eUnr+u1GNjT6u5X-NQ@mail.gmail.com", 
      "from": "brunni@netestate.de", 
      "subject": "Re: NIR SIDETRACK Re: Change Proposal for HttpRange-14"
    }, 
    {
      "url": "http://www.w3.org/mid/20120331184518.GA21150@netestate.de", 
      "replyTo": "http://www.w3.org/mid/CAGnGFM+dfsZvQ212t7RWEfJKWydCrhkG708Gr8bV=t7s3j0_7A@mail.gmail.com", 
      "from": "brunni@netestate.de", 
      "subject": "Re: NIR SIDETRACK Re: Change Proposal for HttpRange-14"
    }, 
    {
      "url": "http://www.w3.org/mid/20120401083544.GA9331@netestate.de", 
      "replyTo": "http://www.w3.org/mid/20120331155303.GA15897@netestate.de", 
      "from": "brunni@netestate.de", 
      "subject": "Re: NIR SIDETRACK Re: Change Proposal for HttpRange-14"
    }, 
    {
      "url": "http://www.w3.org/mid/20120401163118.GA21574@netestate.de", 
      "replyTo": "http://www.w3.org/mid/4F787758.80405@openlinksw.com", 
      "from": "brunni@netestate.de", 
      "subject": "Re: NIR SIDETRACK Re: Change Proposal for HttpRange-14"
    }, 
    {
      "url": "http://www.w3.org/mid/20120403120529.GA5107@netestate.de", 
      "replyTo": "http://www.w3.org/mid/CAGnGFMLqxcp0ykEY9wm86LhjR0Uqn3q-SLwxodm1iHG5=MhAkg@mail.gmail.com", 
      "from": "brunni@netestate.de", 
      "subject": "Re: NIR SIDETRACK Re: Change Proposal for HttpRange-14"
    }, 
    {
      "url": "http://www.w3.org/mid/20120403124214.GA7519@netestate.de", 
      "replyTo": "http://www.w3.org/mid/20120403120529.GA5107@netestate.de", 
      "from": "brunni@netestate.de", 
      "subject": "Re: NIR SIDETRACK Re: Change Proposal for HttpRange-14"
    }, 
    {
      "url": "http://www.w3.org/mid/3858D2E6-4CA5-4537-9D8B-B915CFE9366A@w3.org", 
      "replyTo": "http://www.w3.org/mid/8669B650-0576-46BA-AB53-A84A0A115EA7@astro.gla.ac.uk", 
      "from": "timbl@w3.org", 
      "subject": "Re: Change Proposal for HttpRange-14"
    }, 
    {
      "url": "http://www.w3.org/mid/477AF9B9-48E0-4271-89A3-A94E2EA86562@ihmc.us", 
      "replyTo": "http://www.w3.org/mid/4F6C8FCE.8020708@gmail.com", 
      "from": "phayes@ihmc.us", 
      "subject": "Re: Change Proposal for HttpRange-14"
    }, 
    {
      "url": "http://www.w3.org/mid/4C4BB468-2C75-4F9E-80CB-2641214F5000@w3.org", 
      "replyTo": "http://www.w3.org/mid/6E0960C9-65FC-41DD-9FCD-CA122A48BD44@jenitennison.com", 
      "from": "timbl@w3.org", 
      "subject": "Re: Change Proposal for HttpRange-14"
    }, 
    {
      "url": "http://www.w3.org/mid/4F251EA9-5349-41F8-B6CA-53420845EE31@astro.gla.ac.uk", 
      "replyTo": "http://www.w3.org/mid/CAGnGFMJV0oz-H6+UCJpvjBy8FHWy9Di-tRVcLnU8ZP1=3xUx4w@mail.gmail.com", 
      "from": "norman@astro.gla.ac.uk", 
      "subject": "Re: NIR SIDETRACK Re: Change Proposal for HttpRange-14"
    }, 
    {
      "url": "http://www.w3.org/mid/4F6C7102.7070405@openlinksw.com", 
      "replyTo": "http://www.w3.org/mid/CAMR8oe0Nd37rrCg6GhkpVdAbKHa0hK8-pYNxR+aKMaNZ8fcPwA@mail.gmail.com", 
      "from": "kidehen@openlinksw.com", 
      "subject": "Re: Change Proposal for HttpRange-14"
    }, 
    {
      "url": "http://www.w3.org/mid/4F6C8FCE.8020708@gmail.com", 
      "replyTo": "http://www.w3.org/mid/73656259-599F-491D-BE65-F7A24B42E7B6@ihmc.us", 
      "from": "dave.e.reynolds@gmail.com", 
      "subject": "Re: Change Proposal for HttpRange-14"
    }, 
    {
      "url": "http://www.w3.org/mid/4F6C997B.2020801@openlinksw.com", 
      "replyTo": "http://www.w3.org/mid/4F6C8FCE.8020708@gmail.com", 
      "from": "kidehen@openlinksw.com", 
      "subject": "Re: Change Proposal for HttpRange-14"
    }, 
    {
      "url": "http://www.w3.org/mid/4F6C9995.4030908@openlinksw.com", 
      "replyTo": "http://www.w3.org/mid/CAGnGFMJN9VGsknXLBKx2_Q2m-e-CU1HCxp23yfFWy_Y106-hHA@mail.gmail.com", 
      "from": "kidehen@openlinksw.com", 
      "subject": "Re: Change Proposal for HttpRange-14"
    }, 
    {
      "url": "http://www.w3.org/mid/4F6C9A08.2060902@openlinksw.com", 
      "replyTo": "http://www.w3.org/mid/C2CCB059-575A-4FDA-B1B9-213D8914BFFB@garlik.com", 
      "from": "kidehen@openlinksw.com", 
      "subject": "Re: Change Proposal for HttpRange-14"
    }, 
    {
      "url": "http://www.w3.org/mid/4F6CA418.5050001@gmail.com", 
      "replyTo": "http://www.w3.org/mid/4F6C997B.2020801@openlinksw.com", 
      "from": "dave.e.reynolds@gmail.com", 
      "subject": "Re: Change Proposal for HttpRange-14"
    }, 
    {
      "url": "http://www.w3.org/mid/4F6CA6E4.9060504@openlinksw.com", 
      "replyTo": "http://www.w3.org/mid/EMEW3|08aaed167912ed465e0acb6f68e7a515o2MGCC02hg|ecs.soton.ac.uk|E6F19F02-55F0-4A9F-94C3-43236EFEEBBA@ecs.soton.ac.uk", 
      "from": "kidehen@openlinksw.com", 
      "subject": "Re: Change Proposal for HttpRange-14"
    }, 
    {
      "url": "http://www.w3.org/mid/4F6CA980.2070709@openlinksw.com", 
      "replyTo": "http://www.w3.org/mid/4F6CA418.5050001@gmail.com", 
      "from": "kidehen@openlinksw.com", 
      "subject": "Re: Change Proposal for HttpRange-14"
    }, 
    {
      "url": "http://www.w3.org/mid/4F6D3C9F.5060800@openlinksw.com", 
      "replyTo": "http://www.w3.org/mid/EMEW3|09278775d4ae3fb18e71f4ddf1c6a4d8o2MH5K02hg|ecs.soton.ac.uk|4E6F5568-AF79-4467-8256-F08849EF017D@ecs.soton.ac.uk", 
      "from": "kidehen@openlinksw.com", 
      "subject": "Re: Change Proposal for HttpRange-14"
    }, 
    {
      "url": "http://www.w3.org/mid/4F6D4105.7000507@openlinksw.com", 
      "replyTo": "http://www.w3.org/mid/CAGnGFM+DBoVNVJsjz7DiFETZ6ApSn8pvfOCb_L8zzQyNRpObtw@mail.gmail.com", 
      "from": "kidehen@openlinksw.com", 
      "subject": "Re: Change Proposal for HttpRange-14"
    }, 
    {
      "url": "http://www.w3.org/mid/4F6D9FE3.509@gmail.com", 
      "replyTo": "http://www.w3.org/mid/477AF9B9-48E0-4271-89A3-A94E2EA86562@ihmc.us", 
      "from": "dave.e.reynolds@gmail.com", 
      "subject": "Re: Change Proposal for HttpRange-14"
    }, 
    {
      "url": "http://www.w3.org/mid/4F6DABD4.5090506@openlinksw.com", 
      "replyTo": "http://www.w3.org/mid/CAFfrAFr_c1_5v5140=KLKk6oEnL4SLpLOH7TwqSBdOz7SsAU6A@mail.gmail.com", 
      "from": "kidehen@openlinksw.com", 
      "subject": "Re: Change Proposal for HttpRange-14"
    }, 
    {
      "url": "http://www.w3.org/mid/4F6E0600.8070604@gmail.com", 
      "replyTo": "http://www.w3.org/mid/CAGnGFMJJ_JO-DgwmnbrMC3xagYE2g5m=KMDRZ_R0wMBPnAAL5w@mail.gmail.com", 
      "from": "dave.e.reynolds@gmail.com", 
      "subject": "Re: Change Proposal for HttpRange-14"
    }, 
    {
      "url": "http://www.w3.org/mid/4F6F3DE7.1050802@openlinksw.com", 
      "replyTo": "http://www.w3.org/mid/CBABFE77-7CBF-4D0F-83DD-7422ED04D588@jenitennison.com", 
      "from": "kidehen@openlinksw.com", 
      "subject": "Re: Change Proposal for HttpRange-14"
    }, 
    {
      "url": "http://www.w3.org/mid/4F6F3F59.9080908@openlinksw.com", 
      "replyTo": "http://www.w3.org/mid/20120325100359.GA9806@netestate.de", 
      "from": "kidehen@openlinksw.com", 
      "subject": "Re: Change Proposal for HttpRange-14"
    }, 
    {
      "url": "http://www.w3.org/mid/4F6F450E.7080500@openlinksw.com", 
      "replyTo": "http://www.w3.org/mid/EMEW3|002239814a6a1b6d38b2c4e9de0bac55o2OCJF02hg|ecs.soton.ac.uk|8B5810DD-0844-48BA-8667-B7F240D7F0EC@ecs.soton.ac.uk", 
      "from": "kidehen@openlinksw.com", 
      "subject": "Re: Change Proposal for HttpRange-14"
    }, 
    {
      "url": "http://www.w3.org/mid/4F6F596E.3010904@openlinksw.com", 
      "replyTo": "http://www.w3.org/mid/CADjV5je_p1dkECOwQ2mGJ_A7wzzsjDQjGeD=soXjm4A-1rAPKQ@mail.gmail.com", 
      "from": "kidehen@openlinksw.com", 
      "subject": "Re: Change Proposal for HttpRange-14"
    }, 
    {
      "url": "http://www.w3.org/mid/4F6F5C54.1020202@openlinksw.com", 
      "replyTo": "http://www.w3.org/mid/EMEW3|6675124f5a3f14cbfc088e49b1461166o2OIIj02hg|ecs.soton.ac.uk|6C6F555A-CF8E-4EA5-85FB-F3E890A32CD5@ecs.soton.ac.uk", 
      "from": "kidehen@openlinksw.com", 
      "subject": "Re: Change Proposal for HttpRange-14"
    }, 
    {
      "url": "http://www.w3.org/mid/4F6F62C4.4080203@openlinksw.com", 
      "replyTo": "http://www.w3.org/mid/3858D2E6-4CA5-4537-9D8B-B915CFE9366A@w3.org", 
      "from": "kidehen@openlinksw.com", 
      "subject": "Re: Change Proposal for HttpRange-14"
    }, 
    {
      "url": "http://www.w3.org/mid/4F702186.1090109@gmail.com", 
      "replyTo": "http://www.w3.org/mid/4F6F62C4.4080203@openlinksw.com", 
      "from": "dave.e.reynolds@gmail.com", 
      "subject": "Re: Change Proposal for HttpRange-14"
    }, 
    {
      "url": "http://www.w3.org/mid/4F704E2D.60709@openlinksw.com", 
      "replyTo": "http://www.w3.org/mid/4F702186.1090109@gmail.com", 
      "from": "kidehen@openlinksw.com", 
      "subject": "Re: Change Proposal for HttpRange-14"
    }, 
    {
      "url": "http://www.w3.org/mid/4F70906F.7030601@epimorphics.com", 
      "replyTo": "http://www.w3.org/mid/CAJtGsrhZ1yWMKUYbmWgszXTSfG65-y0vb9vP=KPDW_qJYGjGig@mail.gmail.com", 
      "from": "dave@epimorphics.com", 
      "subject": "Re: Change Proposal for HttpRange-14"
    }, 
    {
      "url": "http://www.w3.org/mid/4F71B999.4070807@openlinksw.com", 
      "replyTo": "http://www.w3.org/mid/CAM=Pv=T2+14++FA0Y+w4cg+XwjVcwUrmrOAPqYGOyU4KSEnimw@mail.gmail.com", 
      "from": "kidehen@openlinksw.com", 
      "subject": "Re: NIR SIDETRACK Re: Change Proposal for HttpRange-14"
    }, 
    {
      "url": "http://www.w3.org/mid/4F71C168.7020600@openlinksw.com", 
      "replyTo": "http://www.w3.org/mid/CAGnGFMJV0oz-H6+UCJpvjBy8FHWy9Di-tRVcLnU8ZP1=3xUx4w@mail.gmail.com", 
      "from": "kidehen@openlinksw.com", 
      "subject": "Re: NIR SIDETRACK Re: Change Proposal for HttpRange-14"
    }, 
    {
      "url": "http://www.w3.org/mid/4F71C568.3080404@openlinksw.com", 
      "replyTo": "http://www.w3.org/mid/CAGnGFMJV0oz-H6+UCJpvjBy8FHWy9Di-tRVcLnU8ZP1=3xUx4w@mail.gmail.com", 
      "from": "kidehen@openlinksw.com", 
      "subject": "Re: NIR SIDETRACK Re: Change Proposal for HttpRange-14"
    }, 
    {
      "url": "http://www.w3.org/mid/4F71E27D.6060600@openlinksw.com", 
      "replyTo": "http://www.w3.org/mid/CB979888.2FFE2%michael.smethurst@bbc.co.uk", 
      "from": "kidehen@openlinksw.com", 
      "subject": "Re: Change Proposal for HttpRange-14"
    }, 
    {
      "url": "http://www.w3.org/mid/4F71F501.1010800@openlinksw.com", 
      "replyTo": "http://www.w3.org/mid/CB97AAF5.3001F%michael.smethurst@bbc.co.uk", 
      "from": "kidehen@openlinksw.com", 
      "subject": "Re: Change Proposal for HttpRange-14"
    }, 
    {
      "url": "http://www.w3.org/mid/4F721E44.6020109@openlinksw.com", 
      "replyTo": "http://www.w3.org/mid/CAKaEYh+8KwswFHZMhUbo0uyh9+_x1DDsLHsJyGxTUW38txnufQ@mail.gmail.com", 
      "from": "kidehen@openlinksw.com", 
      "subject": "Re: Change Proposal for HttpRange-14"
    }, 
    {
      "url": "http://www.w3.org/mid/4F722461.3080401@openlinksw.com", 
      "replyTo": "http://www.w3.org/mid/CAHHRs7i52BgwVBbgDxUCLNoFaYHKABiENx-qyayGZ35_4BnwhA@mail.gmail.com", 
      "from": "kidehen@openlinksw.com", 
      "subject": "Re: Change Proposal for HttpRange-14"
    }, 
    {
      "url": "http://www.w3.org/mid/4F7229E4.9090106@mkbergman.com", 
      "replyTo": "http://www.w3.org/mid/CAGnGFM+P1V+rVvZBdS5B1CaCpqsTFmb7tHkK1oaEj0esPEZwOw@mail.gmail.com", 
      "from": "mike@mkbergman.com", 
      "subject": "Re: NIR SIDETRACK Re: Change Proposal for HttpRange-14"
    }, 
    {
      "url": "http://www.w3.org/mid/4F75E1B0.1010607@openlinksw.com", 
      "replyTo": "http://www.w3.org/mid/CAJtGsriFYE_Zb9LKqLsBu5z33vLtAHqE1oEu_0fCp6OSgXJtuw@mail.gmail.com", 
      "from": "kidehen@openlinksw.com", 
      "subject": "Re: Change Proposal for HttpRange-14"
    }, 
    {
      "url": "http://www.w3.org/mid/4F773527.4040302@openlinksw.com", 
      "replyTo": "http://www.w3.org/mid/CAGnGFM+Uebq-556KOq+P4zEVxM=fnK+0eUnr+u1GNjT6u5X-NQ@mail.gmail.com", 
      "from": "kidehen@openlinksw.com", 
      "subject": "Re: NIR SIDETRACK Re: Change Proposal for HttpRange-14"
    }, 
    {
      "url": "http://www.w3.org/mid/4F787758.80405@openlinksw.com", 
      "replyTo": "http://www.w3.org/mid/20120401083544.GA9331@netestate.de", 
      "from": "kidehen@openlinksw.com", 
      "subject": "Re: NIR SIDETRACK Re: Change Proposal for HttpRange-14"
    }, 
    {
      "url": "http://www.w3.org/mid/4F7879D8.9050708@openlinksw.com", 
      "replyTo": "http://www.w3.org/mid/4F787758.80405@openlinksw.com", 
      "from": "kidehen@openlinksw.com", 
      "subject": "Re: NIR SIDETRACK Re: Change Proposal for HttpRange-14"
    }, 
    {
      "url": "http://www.w3.org/mid/4F78ADC0.3060005@openlinksw.com", 
      "replyTo": "http://www.w3.org/mid/20120401163118.GA21574@netestate.de", 
      "from": "kidehen@openlinksw.com", 
      "subject": "Re: NIR SIDETRACK Re: Change Proposal for HttpRange-14"
    }, 
    {
      "url": "http://www.w3.org/mid/4F791B3D.3070806@openlinksw.com", 
      "replyTo": "http://www.w3.org/mid/1333330978.2181.103785.camel@dbooth-laptop", 
      "from": "kidehen@openlinksw.com", 
      "subject": "Re: NIR SIDETRACK Re: Change Proposal for HttpRange-14"
    }, 
    {
      "url": "http://www.w3.org/mid/4F7C29FD.20803@openlinksw.com", 
      "replyTo": "http://www.w3.org/mid/CBA1D799.303A6%michael.smethurst@bbc.co.uk", 
      "from": "kidehen@openlinksw.com", 
      "subject": "Re: Change Proposal for HttpRange-14"
    }, 
    {
      "url": "http://www.w3.org/mid/4F8D1C70-E67E-4A11-A144-B69DD17B5ECD@jenitennison.com", 
      "replyTo": "http://www.w3.org/mid/1332610564.1830.6.camel@james-laptop", 
      "from": "jeni@jenitennison.com", 
      "subject": "Re: Change Proposal for HttpRange-14"
    }, 
    {
      "url": "http://www.w3.org/mid/5148EDFC-55E0-4914-9A92-CE16801A363D@w3.org", 
      "replyTo": "http://www.w3.org/mid/1332696777.2181.33496.camel@dbooth-laptop", 
      "from": "timbl@w3.org", 
      "subject": "Re: Change Proposal for HttpRange-14"
    }, 
    {
      "url": "http://www.w3.org/mid/5246B8D5-E34B-4CD1-BAF0-7854D8A29255@w3.org", 
      "replyTo": "http://www.w3.org/mid/CB979888.2FFE2%michael.smethurst@bbc.co.uk", 
      "from": "timbl@w3.org", 
      "subject": "Re: Change Proposal for HttpRange-14"
    }, 
    {
      "url": "http://www.w3.org/mid/52E301F960B30049ADEFBCCF1CCAEF590FC5A1E6@OAEXCH4SERVER.oa.oclc.org", 
      "replyTo": "http://www.w3.org/mid/66C5E682-B165-4233-A51B-32F1D0E69DAB@jenitennison.com", 
      "from": "jyoung@oclc.org", 
      "subject": "RE: Change Proposal for HttpRange-14"
    }, 
    {
      "url": "http://www.w3.org/mid/5767B4ED-EB25-42D1-8311-F64825586776@jenitennison.com", 
      "replyTo": "http://www.w3.org/mid/EMEW3|e1f31f22f1d4f694932f08ee13bfaf38o2NA3P02hg|ecs.soton.ac.uk|F7F86D6F-5B6C-4226-A38F-C994FAEB95DB@ecs.soton.ac.uk", 
      "from": "jeni@jenitennison.com", 
      "subject": "Re: Change Proposal for HttpRange-14"
    }, 
    {
      "url": "http://www.w3.org/mid/58C220F8-B09D-4E65-8E4A-76F271D1AA24@jenitennison.com", 
      "replyTo": "http://www.w3.org/mid/6E0960C9-65FC-41DD-9FCD-CA122A48BD44@jenitennison.com", 
      "from": "jeni@jenitennison.com", 
      "subject": "Re: Change Proposal for HttpRange-14"
    }, 
    {
      "url": "http://www.w3.org/mid/597F9F16-2FAF-4B02-9D3B-95A9F24C4031@w3.org", 
      "replyTo": "http://www.w3.org/mid/8F7681C1-48F8-43DE-8712-1AADA7B5264C@jenitennison.com", 
      "from": "timbl@w3.org", 
      "subject": "Re: Change Proposal for HttpRange-14"
    }, 
    {
      "url": "http://www.w3.org/mid/5BCCA964-BC51-4D38-9A32-0160E873B984@3roundstones.com", 
      "replyTo": "http://www.w3.org/mid/1332592732.1912.1.camel@james-laptop", 
      "from": "david@3roundstones.com", 
      "subject": "Re: Change Proposal for HttpRange-14"
    }, 
    {
      "url": "http://www.w3.org/mid/66C5E682-B165-4233-A51B-32F1D0E69DAB@jenitennison.com", 
      "replyTo": "http://www.w3.org/mid/1332530598.4931.11.camel@james-laptop", 
      "from": "jeni@jenitennison.com", 
      "subject": "Re: Change Proposal for HttpRange-14"
    }, 
    {
      "url": "http://www.w3.org/mid/67EAF1C8-4738-4932-9A43-DD703B4C4F55@jenitennison.com", 
      "replyTo": "http://www.w3.org/mid/CAGnGFMJV0oz-H6+UCJpvjBy8FHWy9Di-tRVcLnU8ZP1=3xUx4w@mail.gmail.com", 
      "from": "jeni@jenitennison.com", 
      "subject": "Re: NIR SIDETRACK Re: Change Proposal for HttpRange-14"
    }, 
    {
      "url": "http://www.w3.org/mid/6E0960C9-65FC-41DD-9FCD-CA122A48BD44@jenitennison.com", 
      "replyTo": null, 
      "from": "jeni@jenitennison.com", 
      "subject": "Change Proposal for HttpRange-14"
    }, 
    {
      "url": "http://www.w3.org/mid/72ED5372-B25A-40EF-B070-94588374FACA@jenitennison.com", 
      "replyTo": "http://www.w3.org/mid/E55C54CF-D92C-4E8D-A805-40C181297A4E@w3.org", 
      "from": "jeni@jenitennison.com", 
      "subject": "Re: Change Proposal for HttpRange-14"
    }, 
    {
      "url": "http://www.w3.org/mid/73656259-599F-491D-BE65-F7A24B42E7B6@ihmc.us", 
      "replyTo": "http://www.w3.org/mid/CAGnGFMK+e=BXXxG_DWogoSmxnpn52JZ-bLpYBO6iCV1609irdA@mail.gmail.com", 
      "from": "phayes@ihmc.us", 
      "subject": "Re: Change Proposal for HttpRange-14"
    }, 
    {
      "url": "http://www.w3.org/mid/8669B650-0576-46BA-AB53-A84A0A115EA7@astro.gla.ac.uk", 
      "replyTo": "http://www.w3.org/mid/20120325131938.GA14318@netestate.de", 
      "from": "norman@astro.gla.ac.uk", 
      "subject": "Re: Change Proposal for HttpRange-14"
    }, 
    {
      "url": "http://www.w3.org/mid/87F3BED2-2A7B-4D21-B762-4A902A83CCF5@bris.ac.uk", 
      "replyTo": "http://www.w3.org/mid/CADjV5jdAdi0eLXu++3hkX4dXc0rLtv1QZZt_MTeLGvNgUouKqw@mail.gmail.com", 
      "from": "d.steer@bristol.ac.uk", 
      "subject": "Re: Change Proposal for HttpRange-14"
    }, 
    {
      "url": "http://www.w3.org/mid/8F034508-BE40-4D34-9A99-1AE0C947525E@jenitennison.com", 
      "replyTo": "http://www.w3.org/mid/CAJtGsrhOXhuJn-ZQkeRu07jH92o2nhEtLbYM7VS+3UFHV8_L7w@mail.gmail.com", 
      "from": "jeni@jenitennison.com", 
      "subject": "Re: Change Proposal for HttpRange-14"
    }, 
    {
      "url": "http://www.w3.org/mid/8F7681C1-48F8-43DE-8712-1AADA7B5264C@jenitennison.com", 
      "replyTo": "http://www.w3.org/mid/CAGnGFM+DBoVNVJsjz7DiFETZ6ApSn8pvfOCb_L8zzQyNRpObtw@mail.gmail.com", 
      "from": "jeni@jenitennison.com", 
      "subject": "Re: Change Proposal for HttpRange-14"
    }, 
    {
      "url": "http://www.w3.org/mid/91DA9A68-C960-4917-B1A5-A3C93D92E34E@w3.org", 
      "replyTo": "http://www.w3.org/mid/DCDC38F2-2EE4-4B1B-9731-4A8614810CA1@astro.gla.ac.uk", 
      "from": "timbl@w3.org", 
      "subject": "NIR SIDETRACK Re: Change Proposal for HttpRange-14"
    }, 
    {
      "url": "http://www.w3.org/mid/9362360D-8092-4829-9347-322CCF670D1D@jenitennison.com", 
      "replyTo": "http://www.w3.org/mid/CAGnGFMLtNTNLLF0qmG29kkd5Xj9cgp2qZJeSAtFQTaXcQxDzHw@mail.gmail.com", 
      "from": "jeni@jenitennison.com", 
      "subject": "Re: Change Proposal for HttpRange-14"
    }, 
    {
      "url": "http://www.w3.org/mid/9D86B03C-586A-4C43-BABD-277B5C2E4CCB@jenitennison.com", 
      "replyTo": "http://www.w3.org/mid/20120325100359.GA9806@netestate.de", 
      "from": "jeni@jenitennison.com", 
      "subject": "Re: Change Proposal for HttpRange-14"
    }, 
    {
      "url": "http://www.w3.org/mid/9DB7D905-5129-49EC-8B18-53C165D8E045@3roundstones.com", 
      "replyTo": "http://www.w3.org/mid/67EAF1C8-4738-4932-9A43-DD703B4C4F55@jenitennison.com", 
      "from": "david@3roundstones.com", 
      "subject": "Re: NIR SIDETRACK Re: Change Proposal for HttpRange-14"
    }, 
    {
      "url": "http://www.w3.org/mid/AA8CF3FF-BF3E-4D2F-B4FB-5FA0D2AEB55A@w3.org", 
      "replyTo": "http://www.w3.org/mid/3858D2E6-4CA5-4537-9D8B-B915CFE9366A@w3.org", 
      "from": "timbl@w3.org", 
      "subject": "Change Proposal  25  for HttpRange-14"
    }, 
    {
      "url": "http://www.w3.org/mid/AE14D65A-7721-4149-9788-60305285116B@astro.gla.ac.uk", 
      "replyTo": "http://www.w3.org/mid/20120328213504.GA10598@netestate.de", 
      "from": "norman@astro.gla.ac.uk", 
      "subject": "Re: NIR SIDETRACK Re: Change Proposal for HttpRange-14"
    }, 
    {
      "url": "http://www.w3.org/mid/B5C1F24E-D304-4160-903D-F8C07C1EE648@astro.gla.ac.uk", 
      "replyTo": "http://www.w3.org/mid/CAGnGFMLaE6n9Lxgekou3wHZEeT1YZdwsw2e+vQ4bUoWYybKRQw@mail.gmail.com", 
      "from": "norman@astro.gla.ac.uk", 
      "subject": "Re: NIR SIDETRACK Re: Change Proposal for HttpRange-14"
    }, 
    {
      "url": "http://www.w3.org/mid/B8EF7418-93EA-436D-BDEB-45766907188C@w3.org", 
      "replyTo": "http://www.w3.org/mid/477AF9B9-48E0-4271-89A3-A94E2EA86562@ihmc.us", 
      "from": "timbl@w3.org", 
      "subject": "Re: Change Proposal for HttpRange-14"
    }, 
    {
      "url": "http://www.w3.org/mid/BD501D8F-C62F-4839-B330-E2C6D0B6F86C@ihmc.us", 
      "replyTo": "http://www.w3.org/mid/CAK4ZFVEOcj00mLkvFrto=F_8NLxELz=aior70Y0T6pwbszhpYw@mail.gmail.com", 
      "from": "phayes@ihmc.us", 
      "subject": "Re: Change Proposal for HttpRange-14"
    }, 
    {
      "url": "http://www.w3.org/mid/C2CCB059-575A-4FDA-B1B9-213D8914BFFB@garlik.com", 
      "replyTo": "http://www.w3.org/mid/CAGnGFMJN9VGsknXLBKx2_Q2m-e-CU1HCxp23yfFWy_Y106-hHA@mail.gmail.com", 
      "from": "steve.harris@garlik.com", 
      "subject": "Re: Change Proposal for HttpRange-14"
    }, 
    {
      "url": "http://www.w3.org/mid/CAC_nr_r5cqCJfmPa8-mFpO5-x1ogiTm5fRBx2fWr72CVdyoRrA@mail.gmail.com", 
      "replyTo": "http://www.w3.org/mid/CAGnGFMJV0oz-H6+UCJpvjBy8FHWy9Di-tRVcLnU8ZP1=3xUx4w@mail.gmail.com", 
      "from": "leigh@ldodds.com", 
      "subject": "Re: NIR SIDETRACK Re: Change Proposal for HttpRange-14"
    }, 
    {
      "url": "http://www.w3.org/mid/CAC_nr_rwoWs+ypDyrDOwrjsoGi5z4fNq8wPjm7fp50NKPo_u9w@mail.gmail.com", 
      "replyTo": "http://www.w3.org/mid/B8EF7418-93EA-436D-BDEB-45766907188C@w3.org", 
      "from": "leigh@ldodds.com", 
      "subject": "Re: Change Proposal for HttpRange-14"
    }, 
    {
      "url": "http://www.w3.org/mid/CADjV5jdAdi0eLXu++3hkX4dXc0rLtv1QZZt_MTeLGvNgUouKqw@mail.gmail.com", 
      "replyTo": "http://www.w3.org/mid/CAFfrAFrDOsZxT6___9Ht4Ph3-6i-YayT=H9eWEij5sPwJdYX9Q@mail.gmail.com", 
      "from": "lindstream@gmail.com", 
      "subject": "Re: Change Proposal for HttpRange-14"
    }, 
    {
      "url": "http://www.w3.org/mid/CADjV5je_p1dkECOwQ2mGJ_A7wzzsjDQjGeD=soXjm4A-1rAPKQ@mail.gmail.com", 
      "replyTo": "http://www.w3.org/mid/20120325131938.GA14318@netestate.de", 
      "from": "lindstream@gmail.com", 
      "subject": "Re: Change Proposal for HttpRange-14"
    }, 
    {
      "url": "http://www.w3.org/mid/CADjV5jeh+knxP1drQDx1CV712m3LWAjKYY-bza+9XuuRL0kmuA@mail.gmail.com", 
      "replyTo": "http://www.w3.org/mid/CAFfrAFr_c1_5v5140=KLKk6oEnL4SLpLOH7TwqSBdOz7SsAU6A@mail.gmail.com", 
      "from": "lindstream@gmail.com", 
      "subject": "Re: Change Proposal for HttpRange-14"
    }, 
    {
      "url": "http://www.w3.org/mid/CAFfrAFo1E0jwRZjNraaOoYhq8F3Y-Uargm23eEqqFk0_CgBsOQ@mail.gmail.com", 
      "replyTo": "http://www.w3.org/mid/CAKaEYhJmTUCLDHXNahoQ1aW9jNKT489Ogu3aUgq36NpbHuZGJg@mail.gmail.com", 
      "from": "danbri@danbri.org", 
      "subject": "Re: Change Proposal for HttpRange-14"
    }, 
    {
      "url": "http://www.w3.org/mid/CAFfrAFoP=mh9ah5QHCiNXKxDP+Nd19S44aNbFi1cfSZbhWncKA@mail.gmail.com", 
      "replyTo": "http://www.w3.org/mid/B8EF7418-93EA-436D-BDEB-45766907188C@w3.org", 
      "from": "danbri@danbri.org", 
      "subject": "Re: Change Proposal for HttpRange-14"
    }, 
    {
      "url": "http://www.w3.org/mid/CAFfrAFpYcfc9jeBzqpjU6ckCL63AmY=cdtDzH0ZgrocQ-U_uLw@mail.gmail.com", 
      "replyTo": "http://www.w3.org/mid/20120325100359.GA9806@netestate.de", 
      "from": "danbri@danbri.org", 
      "subject": "Re: Change Proposal for HttpRange-14"
    }, 
    {
      "url": "http://www.w3.org/mid/CAFfrAFrDOsZxT6___9Ht4Ph3-6i-YayT=H9eWEij5sPwJdYX9Q@mail.gmail.com", 
      "replyTo": "http://www.w3.org/mid/4F6E0600.8070604@gmail.com", 
      "from": "danbri@danbri.org", 
      "subject": "Re: Change Proposal for HttpRange-14"
    }, 
    {
      "url": "http://www.w3.org/mid/CAFfrAFr_ZQFtqJ_WY0m68mkAq8EBApCMZ6v_KHcVhFDMR-gzeQ@mail.gmail.com", 
      "replyTo": "http://www.w3.org/mid/4F6D9FE3.509@gmail.com", 
      "from": "danbri@danbri.org", 
      "subject": "Re: Change Proposal for HttpRange-14"
    }, 
    {
      "url": "http://www.w3.org/mid/CAFfrAFr_c1_5v5140=KLKk6oEnL4SLpLOH7TwqSBdOz7SsAU6A@mail.gmail.com", 
      "replyTo": "http://www.w3.org/mid/73656259-599F-491D-BE65-F7A24B42E7B6@ihmc.us", 
      "from": "danbri@danbri.org", 
      "subject": "Re: Change Proposal for HttpRange-14"
    }, 
    {
      "url": "http://www.w3.org/mid/CAGnGFM+DBoVNVJsjz7DiFETZ6ApSn8pvfOCb_L8zzQyNRpObtw@mail.gmail.com", 
      "replyTo": "http://www.w3.org/mid/6E0960C9-65FC-41DD-9FCD-CA122A48BD44@jenitennison.com", 
      "from": "rees@mumble.net", 
      "subject": "Re: Change Proposal for HttpRange-14"
    }, 
    {
      "url": "http://www.w3.org/mid/CAGnGFM+P1V+rVvZBdS5B1CaCpqsTFmb7tHkK1oaEj0esPEZwOw@mail.gmail.com", 
      "replyTo": "http://www.w3.org/mid/CAC_nr_r5cqCJfmPa8-mFpO5-x1ogiTm5fRBx2fWr72CVdyoRrA@mail.gmail.com", 
      "from": "rees@mumble.net", 
      "subject": "Re: NIR SIDETRACK Re: Change Proposal for HttpRange-14"
    }, 
    {
      "url": "http://www.w3.org/mid/CAGnGFM+Q+CyCY_Moc=7mnKA0uDB6Um1dMP2aH9BMqV6rTKDHSQ@mail.gmail.com", 
      "replyTo": "http://www.w3.org/mid/4F7229E4.9090106@mkbergman.com", 
      "from": "rees@mumble.net", 
      "subject": "Re: NIR SIDETRACK Re: Change Proposal for HttpRange-14"
    }, 
    {
      "url": "http://www.w3.org/mid/CAGnGFM+TfVW=Oom9JpNFWK9tpQNO3Wv0rh+Q1XxwQP3JhUeJ-w@mail.gmail.com", 
      "replyTo": "http://www.w3.org/mid/20120327143732.GA26477@netestate.de", 
      "from": "rees@mumble.net", 
      "subject": "Re: NIR SIDETRACK Re: Change Proposal for HttpRange-14"
    }, 
    {
      "url": "http://www.w3.org/mid/CAGnGFM+Uebq-556KOq+P4zEVxM=fnK+0eUnr+u1GNjT6u5X-NQ@mail.gmail.com", 
      "replyTo": "http://www.w3.org/mid/20120331151333.GA14808@netestate.de", 
      "from": "rees@mumble.net", 
      "subject": "Re: NIR SIDETRACK Re: Change Proposal for HttpRange-14"
    }, 
    {
      "url": "http://www.w3.org/mid/CAGnGFM+dfsZvQ212t7RWEfJKWydCrhkG708Gr8bV=t7s3j0_7A@mail.gmail.com", 
      "replyTo": "http://www.w3.org/mid/20120331120557.GA9772@netestate.de", 
      "from": "rees@mumble.net", 
      "subject": "Re: NIR SIDETRACK Re: Change Proposal for HttpRange-14"
    }, 
    {
      "url": "http://www.w3.org/mid/CAGnGFMJ3EP+9R2krbA6rDq8Y13aVk+A+6_DrPSvUx0rGv6Z_4g@mail.gmail.com", 
      "replyTo": "http://www.w3.org/mid/AA8CF3FF-BF3E-4D2F-B4FB-5FA0D2AEB55A@w3.org", 
      "from": "rees@mumble.net", 
      "subject": "Re: Change Proposal 25 for HttpRange-14"
    }, 
    {
      "url": "http://www.w3.org/mid/CAGnGFMJJ_JO-DgwmnbrMC3xagYE2g5m=KMDRZ_R0wMBPnAAL5w@mail.gmail.com", 
      "replyTo": "http://www.w3.org/mid/5767B4ED-EB25-42D1-8311-F64825586776@jenitennison.com", 
      "from": "rees@mumble.net", 
      "subject": "Re: Change Proposal for HttpRange-14"
    }, 
    {
      "url": "http://www.w3.org/mid/CAGnGFMJN9VGsknXLBKx2_Q2m-e-CU1HCxp23yfFWy_Y106-hHA@mail.gmail.com", 
      "replyTo": "http://www.w3.org/mid/CAKaEYhJmTUCLDHXNahoQ1aW9jNKT489Ogu3aUgq36NpbHuZGJg@mail.gmail.com", 
      "from": "rees@mumble.net", 
      "subject": "Re: Change Proposal for HttpRange-14"
    }, 
    {
      "url": "http://www.w3.org/mid/CAGnGFMJR=34-d8FxK=9t0cxkuBkL-UNpddM=YZEv4dOk-97gUQ@mail.gmail.com", 
      "replyTo": "http://www.w3.org/mid/4C4BB468-2C75-4F9E-80CB-2641214F5000@w3.org", 
      "from": "rees@mumble.net", 
      "subject": "Re: Change Proposal for HttpRange-14"
    }, 
    {
      "url": "http://www.w3.org/mid/CAGnGFMJV0oz-H6+UCJpvjBy8FHWy9Di-tRVcLnU8ZP1=3xUx4w@mail.gmail.com", 
      "replyTo": "http://www.w3.org/mid/20120327115202.GA22395@netestate.de", 
      "from": "rees@mumble.net", 
      "subject": "Re: NIR SIDETRACK Re: Change Proposal for HttpRange-14"
    }, 
    {
      "url": "http://www.w3.org/mid/CAGnGFMJWxpDbYPzUqfacaNp5eAr0Wi3DDqjLm2OSzcCuWSG0fg@mail.gmail.com", 
      "replyTo": "http://www.w3.org/mid/09147104-5C3E-410A-B37B-3202C82A78A9@jenitennison.com", 
      "from": "rees@mumble.net", 
      "subject": "Re: NIR SIDETRACK Re: Change Proposal for HttpRange-14"
    }, 
    {
      "url": "http://www.w3.org/mid/CAGnGFMK+e=BXXxG_DWogoSmxnpn52JZ-bLpYBO6iCV1609irdA@mail.gmail.com", 
      "replyTo": "http://www.w3.org/mid/6E0960C9-65FC-41DD-9FCD-CA122A48BD44@jenitennison.com", 
      "from": "rees@mumble.net", 
      "subject": "Re: Change Proposal for HttpRange-14"
    }, 
    {
      "url": "http://www.w3.org/mid/CAGnGFMKXarSLyQv5zcN3d5KDFz46i4k74RXoz=XQwqr2Um0RCw@mail.gmail.com", 
      "replyTo": "http://www.w3.org/mid/1333074023.2181.84542.camel@dbooth-laptop", 
      "from": "rees@mumble.net", 
      "subject": "Re: NIR SIDETRACK Re: Change Proposal for HttpRange-14"
    }, 
    {
      "url": "http://www.w3.org/mid/CAGnGFML19FBKQsL8YAG-wqbRQAgtSD9bRzmEUtji+EWoPOBXzA@mail.gmail.com", 
      "replyTo": "http://www.w3.org/mid/4F71C168.7020600@openlinksw.com", 
      "from": "rees@mumble.net", 
      "subject": "Re: NIR SIDETRACK Re: Change Proposal for HttpRange-14"
    }, 
    {
      "url": "http://www.w3.org/mid/CAGnGFMLFJTLd4wFP_mGtev3RU4vva2=MpMHdqy14f7WMGSS=NA@mail.gmail.com", 
      "replyTo": "http://www.w3.org/mid/67EAF1C8-4738-4932-9A43-DD703B4C4F55@jenitennison.com", 
      "from": "rees@mumble.net", 
      "subject": "Re: NIR SIDETRACK Re: Change Proposal for HttpRange-14"
    }, 
    {
      "url": "http://www.w3.org/mid/CAGnGFMLaE6n9Lxgekou3wHZEeT1YZdwsw2e+vQ4bUoWYybKRQw@mail.gmail.com", 
      "replyTo": "http://www.w3.org/mid/4F251EA9-5349-41F8-B6CA-53420845EE31@astro.gla.ac.uk", 
      "from": "rees@mumble.net", 
      "subject": "Re: NIR SIDETRACK Re: Change Proposal for HttpRange-14"
    }, 
    {
      "url": "http://www.w3.org/mid/CAGnGFMLqxcp0ykEY9wm86LhjR0Uqn3q-SLwxodm1iHG5=MhAkg@mail.gmail.com", 
      "replyTo": "http://www.w3.org/mid/20120401083544.GA9331@netestate.de", 
      "from": "rees@mumble.net", 
      "subject": "Re: NIR SIDETRACK Re: Change Proposal for HttpRange-14"
    }, 
    {
      "url": "http://www.w3.org/mid/CAGnGFMLtNTNLLF0qmG29kkd5Xj9cgp2qZJeSAtFQTaXcQxDzHw@mail.gmail.com", 
      "replyTo": "http://www.w3.org/mid/6E0960C9-65FC-41DD-9FCD-CA122A48BD44@jenitennison.com", 
      "from": "rees@mumble.net", 
      "subject": "Re: Change Proposal for HttpRange-14"
    }, 
    {
      "url": "http://www.w3.org/mid/CAGnGFMLucr9xoGrDybtc7GWp5xM20ZW0XetYrN+i_OBeY2PNqQ@mail.gmail.com", 
      "replyTo": "http://www.w3.org/mid/8F7681C1-48F8-43DE-8712-1AADA7B5264C@jenitennison.com", 
      "from": "rees@mumble.net", 
      "subject": "Re: Change Proposal for HttpRange-14"
    }, 
    {
      "url": "http://www.w3.org/mid/CAHHRs7gHEMM+Wwy7_=KXsHgOiYs4M+THmxqRTW2bGVcHKkZp4w@mail.gmail.com", 
      "replyTo": "http://www.w3.org/mid/CAMR8oe0Nd37rrCg6GhkpVdAbKHa0hK8-pYNxR+aKMaNZ8fcPwA@mail.gmail.com", 
      "from": "giovanni.tummarello@deri.org", 
      "subject": "Re: Change Proposal for HttpRange-14"
    }, 
    {
      "url": "http://www.w3.org/mid/CAHHRs7i52BgwVBbgDxUCLNoFaYHKABiENx-qyayGZ35_4BnwhA@mail.gmail.com", 
      "replyTo": "http://www.w3.org/mid/CAJtGsrhOXhuJn-ZQkeRu07jH92o2nhEtLbYM7VS+3UFHV8_L7w@mail.gmail.com", 
      "from": "giovanni.tummarello@deri.org", 
      "subject": "Re: Change Proposal for HttpRange-14"
    }, 
    {
      "url": "http://www.w3.org/mid/CAJtGsrgBOnwXg5yvYr_wwkBfqv1u9yfXbzOjHXqg6WHBm6Vcmw@mail.gmail.com", 
      "replyTo": "http://www.w3.org/mid/4F75E1B0.1010607@openlinksw.com", 
      "from": "tom.heath@talis.com", 
      "subject": "Re: Change Proposal for HttpRange-14"
    }, 
    {
      "url": "http://www.w3.org/mid/CAJtGsrgdzSZ0MSCXFpPy+vn=Q_S7k6HCAjev0UD9x6NnoNeVFQ@mail.gmail.com", 
      "replyTo": "http://www.w3.org/mid/CAHHRs7i52BgwVBbgDxUCLNoFaYHKABiENx-qyayGZ35_4BnwhA@mail.gmail.com", 
      "from": "tom.heath@talis.com", 
      "subject": "Re: Change Proposal for HttpRange-14"
    }, 
    {
      "url": "http://www.w3.org/mid/CAJtGsrhOXhuJn-ZQkeRu07jH92o2nhEtLbYM7VS+3UFHV8_L7w@mail.gmail.com", 
      "replyTo": "http://www.w3.org/mid/094D59EA-AAB2-4063-A0AC-2EA56C299DE8@jenitennison.com", 
      "from": "tom.heath@talis.com", 
      "subject": "Re: Change Proposal for HttpRange-14"
    }, 
    {
      "url": "http://www.w3.org/mid/CAJtGsrhZ1yWMKUYbmWgszXTSfG65-y0vb9vP=KPDW_qJYGjGig@mail.gmail.com", 
      "replyTo": "http://www.w3.org/mid/C2CCB059-575A-4FDA-B1B9-213D8914BFFB@garlik.com", 
      "from": "tom.heath@talis.com", 
      "subject": "Re: Change Proposal for HttpRange-14"
    }, 
    {
      "url": "http://www.w3.org/mid/CAJtGsriFYE_Zb9LKqLsBu5z33vLtAHqE1oEu_0fCp6OSgXJtuw@mail.gmail.com", 
      "replyTo": "http://www.w3.org/mid/CB979888.2FFE2%michael.smethurst@bbc.co.uk", 
      "from": "tom.heath@talis.com", 
      "subject": "Re: Change Proposal for HttpRange-14"
    }, 
    {
      "url": "http://www.w3.org/mid/CAJtGsriGEKyGHb_PrV+p+CJ2nmHABmj=HNax+19TV-qUuiMEag@mail.gmail.com", 
      "replyTo": "http://www.w3.org/mid/4F70906F.7030601@epimorphics.com", 
      "from": "tom.heath@talis.com", 
      "subject": "Re: Change Proposal for HttpRange-14"
    }, 
    {
      "url": "http://www.w3.org/mid/CAK4ZFVEOcj00mLkvFrto=F_8NLxELz=aior70Y0T6pwbszhpYw@mail.gmail.com", 
      "replyTo": "http://www.w3.org/mid/477AF9B9-48E0-4271-89A3-A94E2EA86562@ihmc.us", 
      "from": "bernard.vatant@mondeca.com", 
      "subject": "Re: Change Proposal for HttpRange-14"
    }, 
    {
      "url": "http://www.w3.org/mid/CAK9bEGxusUKZoG2wLTFr1LwnOh0y8AZDHgv8ZJmp+CxjeF2wNQ@mail.gmail.com", 
      "replyTo": "http://www.w3.org/mid/AA8CF3FF-BF3E-4D2F-B4FB-5FA0D2AEB55A@w3.org", 
      "from": "erikis@kth.se", 
      "subject": "Re: Change Proposal 25 for HttpRange-14"
    }, 
    {
      "url": "http://www.w3.org/mid/CAKaEYh+8KwswFHZMhUbo0uyh9+_x1DDsLHsJyGxTUW38txnufQ@mail.gmail.com", 
      "replyTo": "http://www.w3.org/mid/8F034508-BE40-4D34-9A99-1AE0C947525E@jenitennison.com", 
      "from": "melvincarvalho@gmail.com", 
      "subject": "Re: Change Proposal for HttpRange-14"
    }, 
    {
      "url": "http://www.w3.org/mid/CAKaEYhJmTUCLDHXNahoQ1aW9jNKT489Ogu3aUgq36NpbHuZGJg@mail.gmail.com", 
      "replyTo": "http://www.w3.org/mid/CAHHRs7gHEMM+Wwy7_=KXsHgOiYs4M+THmxqRTW2bGVcHKkZp4w@mail.gmail.com", 
      "from": "melvincarvalho@gmail.com", 
      "subject": "Re: Change Proposal for HttpRange-14"
    }, 
    {
      "url": "http://www.w3.org/mid/CAM=Pv=T2+14++FA0Y+w4cg+XwjVcwUrmrOAPqYGOyU4KSEnimw@mail.gmail.com", 
      "replyTo": "http://www.w3.org/mid/91DA9A68-C960-4917-B1A5-A3C93D92E34E@w3.org", 
      "from": "danny.ayers@gmail.com", 
      "subject": "Re: NIR SIDETRACK Re: Change Proposal for HttpRange-14"
    }, 
    {
      "url": "http://www.w3.org/mid/CAMR8oe0Nd37rrCg6GhkpVdAbKHa0hK8-pYNxR+aKMaNZ8fcPwA@mail.gmail.com", 
      "replyTo": "http://www.w3.org/mid/6E0960C9-65FC-41DD-9FCD-CA122A48BD44@jenitennison.com", 
      "from": "sergio.fernandez@fundacionctic.org", 
      "subject": "Re: Change Proposal for HttpRange-14"
    }, 
    {
      "url": "http://www.w3.org/mid/CB979888.2FFE2%25michael.smethurst@bbc.co.uk", 
      "replyTo": "http://www.w3.org/mid/CAJtGsrhOXhuJn-ZQkeRu07jH92o2nhEtLbYM7VS+3UFHV8_L7w@mail.gmail.com", 
      "from": "michael.smethurst@bbc.co.uk", 
      "subject": "Re: Change Proposal for HttpRange-14"
    }, 
    {
      "url": "http://www.w3.org/mid/CB97AAF5.3001F%25michael.smethurst@bbc.co.uk", 
      "replyTo": "http://www.w3.org/mid/4F71E27D.6060600@openlinksw.com", 
      "from": "michael.smethurst@bbc.co.uk", 
      "subject": "Re: Change Proposal for HttpRange-14"
    }, 
    {
      "url": "http://www.w3.org/mid/CB989FDB.3007D%25michael.smethurst@bbc.co.uk", 
      "replyTo": "http://www.w3.org/mid/4F71F501.1010800@openlinksw.com", 
      "from": "michael.smethurst@bbc.co.uk", 
      "subject": "Re: Change Proposal for HttpRange-14"
    }, 
    {
      "url": "http://www.w3.org/mid/CBA1D799.303A6%25michael.smethurst@bbc.co.uk", 
      "replyTo": "http://www.w3.org/mid/CAJtGsriFYE_Zb9LKqLsBu5z33vLtAHqE1oEu_0fCp6OSgXJtuw@mail.gmail.com", 
      "from": "michael.smethurst@bbc.co.uk", 
      "subject": "Re: Change Proposal for HttpRange-14"
    }, 
    {
      "url": "http://www.w3.org/mid/CBABFE77-7CBF-4D0F-83DD-7422ED04D588@jenitennison.com", 
      "replyTo": "http://www.w3.org/mid/20120324231646.GA26121@netestate.de", 
      "from": "jeni@jenitennison.com", 
      "subject": "Re: Change Proposal for HttpRange-14"
    }, 
    {
      "url": "http://www.w3.org/mid/D0920A37-467F-4275-A756-1B0A5D5E769C@ihmc.us", 
      "replyTo": "http://www.w3.org/mid/CAM=Pv=T2+14++FA0Y+w4cg+XwjVcwUrmrOAPqYGOyU4KSEnimw@mail.gmail.com", 
      "from": "phayes@ihmc.us", 
      "subject": "Re: NIR SIDETRACK Re: Change Proposal for HttpRange-14"
    }, 
    {
      "url": "http://www.w3.org/mid/D4654800-BDCB-4C09-BACB-D97B90B4A03B@ihmc.us", 
      "replyTo": "http://www.w3.org/mid/CAFfrAFr_c1_5v5140=KLKk6oEnL4SLpLOH7TwqSBdOz7SsAU6A@mail.gmail.com", 
      "from": "phayes@ihmc.us", 
      "subject": "Re: Change Proposal for HttpRange-14"
    }, 
    {
      "url": "http://www.w3.org/mid/D8CF4CC8-8D2F-47D3-AD56-DE5D01724C06@jenitennison.com", 
      "replyTo": "http://www.w3.org/mid/1332534274.1862.5.camel@james-laptop", 
      "from": "jeni@jenitennison.com", 
      "subject": "Re: Change Proposal for HttpRange-14"
    }, 
    {
      "url": "http://www.w3.org/mid/DAE0EB3C-0EC0-45C3-8281-6B398051EFEF@jenitennison.com", 
      "replyTo": "http://www.w3.org/mid/1332592732.1912.1.camel@james-laptop", 
      "from": "jeni@jenitennison.com", 
      "subject": "Re: Change Proposal for HttpRange-14"
    }, 
    {
      "url": "http://www.w3.org/mid/DCDC38F2-2EE4-4B1B-9731-4A8614810CA1@astro.gla.ac.uk", 
      "replyTo": "http://www.w3.org/mid/3858D2E6-4CA5-4537-9D8B-B915CFE9366A@w3.org", 
      "from": "norman@astro.gla.ac.uk", 
      "subject": "Re: Change Proposal for HttpRange-14"
    }, 
    {
      "url": "http://www.w3.org/mid/E4216A5B-5E9E-4433-9FC3-594B3A395894@jenitennison.com", 
      "replyTo": "http://www.w3.org/mid/20120324215926.GA24475@netestate.de", 
      "from": "jeni@jenitennison.com", 
      "subject": "Re: Change Proposal for HttpRange-14"
    }, 
    {
      "url": "http://www.w3.org/mid/E55C54CF-D92C-4E8D-A805-40C181297A4E@w3.org", 
      "replyTo": "http://www.w3.org/mid/9D86B03C-586A-4C43-BABD-277B5C2E4CCB@jenitennison.com", 
      "from": "timbl@w3.org", 
      "subject": "Re: Change Proposal for HttpRange-14"
    }, 
    {
      "url": "http://www.w3.org/mid/E8814EA7-FF59-4EEE-BF4A-4F72DAF65FC6@jenitennison.com", 
      "replyTo": "http://www.w3.org/mid/1332549492.1843.27.camel@james-laptop", 
      "from": "jeni@jenitennison.com", 
      "subject": "Re: Change Proposal for HttpRange-14"
    }, 
    {
      "url": "http://www.w3.org/mid/EC73CFBE-EC6E-4A12-9304-9148344C9CDC@jenitennison.com", 
      "replyTo": "http://www.w3.org/mid/CAGnGFMJJ_JO-DgwmnbrMC3xagYE2g5m=KMDRZ_R0wMBPnAAL5w@mail.gmail.com", 
      "from": "jeni@jenitennison.com", 
      "subject": "Re: Change Proposal for HttpRange-14"
    }, 
    {
      "url": "http://www.w3.org/mid/EMEW3|002239814a6a1b6d38b2c4e9de0bac55o2OCJF02hg|ecs.soton.ac.uk|8B5810DD-0844-48BA-8667-B7F240D7F0EC@ecs.soton.ac.uk", 
      "replyTo": "http://www.w3.org/mid/20120325100359.GA9806@netestate.de", 
      "from": "hg@ecs.soton.ac.uk", 
      "subject": "Re: Change Proposal for HttpRange-14"
    }, 
    {
      "url": "http://www.w3.org/mid/EMEW3|08aaed167912ed465e0acb6f68e7a515o2MGCC02hg|ecs.soton.ac.uk|E6F19F02-55F0-4A9F-94C3-43236EFEEBBA@ecs.soton.ac.uk", 
      "replyTo": "http://www.w3.org/mid/6E0960C9-65FC-41DD-9FCD-CA122A48BD44@jenitennison.com", 
      "from": "hg@ecs.soton.ac.uk", 
      "subject": "Re: Change Proposal for HttpRange-14"
    }, 
    {
      "url": "http://www.w3.org/mid/EMEW3|09278775d4ae3fb18e71f4ddf1c6a4d8o2MH5K02hg|ecs.soton.ac.uk|4E6F5568-AF79-4467-8256-F08849EF017D@ecs.soton.ac.uk", 
      "replyTo": "http://www.w3.org/mid/4F6CA6E4.9060504@openlinksw.com", 
      "from": "hg@ecs.soton.ac.uk", 
      "subject": "Re: Change Proposal for HttpRange-14"
    }, 
    {
      "url": "http://www.w3.org/mid/EMEW3|435ac0f210ba228e8379b4050ce617bco2MJfG02hg|ecs.soton.ac.uk|3FB4D5E2-BCA2-4522-AF78-AD3CFE9CB974@ecs.soton.ac.uk", 
      "replyTo": "http://www.w3.org/mid/1332530598.4931.11.camel@james-laptop", 
      "from": "hg@ecs.soton.ac.uk", 
      "subject": "Re: Change Proposal for HttpRange-14"
    }, 
    {
      "url": "http://www.w3.org/mid/EMEW3|6675124f5a3f14cbfc088e49b1461166o2OIIj02hg|ecs.soton.ac.uk|6C6F555A-CF8E-4EA5-85FB-F3E890A32CD5@ecs.soton.ac.uk", 
      "replyTo": "http://www.w3.org/mid/4F6F450E.7080500@openlinksw.com", 
      "from": "hg@ecs.soton.ac.uk", 
      "subject": "Re: Change Proposal for HttpRange-14"
    }, 
    {
      "url": "http://www.w3.org/mid/EMEW3|c6a1dbcc90044c46c5009a2e20c57631o2NBdd02hg|ecs.soton.ac.uk|3C6FCE34-FCD4-4064-8072-51105468882D@ecs.soton.ac.uk", 
      "replyTo": "http://www.w3.org/mid/5767B4ED-EB25-42D1-8311-F64825586776@jenitennison.com", 
      "from": "hg@ecs.soton.ac.uk", 
      "subject": "Re: Change Proposal for HttpRange-14"
    }, 
    {
      "url": "http://www.w3.org/mid/EMEW3|e1f31f22f1d4f694932f08ee13bfaf38o2NA3P02hg|ecs.soton.ac.uk|F7F86D6F-5B6C-4226-A38F-C994FAEB95DB@ecs.soton.ac.uk", 
      "replyTo": "http://www.w3.org/mid/E8814EA7-FF59-4EEE-BF4A-4F72DAF65FC6@jenitennison.com", 
      "from": "hg@ecs.soton.ac.uk", 
      "subject": "Re: Change Proposal for HttpRange-14"
    }, 
    {
      "url": "http://www.w3.org/mid/FD84F354-DE7E-4A69-8ED1-B8E2527390CC@jenitennison.com", 
      "replyTo": "http://www.w3.org/mid/B8EF7418-93EA-436D-BDEB-45766907188C@w3.org", 
      "from": "jeni@jenitennison.com", 
      "subject": "Re: Change Proposal for HttpRange-14"
    }, 
    {
      "url": "http://www.w3.org/mid/FF625B84-FC10-46D9-ABD7-80EAF45258DC@jenitennison.com", 
      "replyTo": "http://www.w3.org/mid/CAGnGFMLucr9xoGrDybtc7GWp5xM20ZW0XetYrN+i_OBeY2PNqQ@mail.gmail.com", 
      "from": "jeni@jenitennison.com", 
      "subject": "Re: Change Proposal for HttpRange-14"
    }
  ], 
  "links": [
    {
      "source": 89, 
      "target": 127
    }, 
    {
      "source": 160, 
      "target": 2
    }, 
    {
      "source": 79, 
      "target": 2
    }, 
    {
      "source": 3, 
      "target": 79
    }, 
    {
      "source": 74, 
      "target": 79
    }, 
    {
      "source": 150, 
      "target": 3
    }, 
    {
      "source": 4, 
      "target": 150
    }, 
    {
      "source": 118, 
      "target": 32
    }, 
    {
      "source": 87, 
      "target": 109
    }, 
    {
      "source": 43, 
      "target": 109
    }, 
    {
      "source": 155, 
      "target": 4
    }, 
    {
      "source": 128, 
      "target": 87
    }, 
    {
      "source": 77, 
      "target": 87
    }, 
    {
      "source": 126, 
      "target": 26
    }, 
    {
      "source": 66, 
      "target": 26
    }, 
    {
      "source": 10, 
      "target": 26
    }, 
    {
      "source": 28, 
      "target": 126
    }, 
    {
      "source": 67, 
      "target": 66
    }, 
    {
      "source": 27, 
      "target": 66
    }, 
    {
      "source": 68, 
      "target": 27
    }, 
    {
      "source": 69, 
      "target": 11
    }, 
    {
      "source": 29, 
      "target": 28
    }, 
    {
      "source": 44, 
      "target": 31
    }, 
    {
      "source": 95, 
      "target": 31
    }, 
    {
      "source": 137, 
      "target": 31
    }, 
    {
      "source": 163, 
      "target": 155
    }, 
    {
      "source": 5, 
      "target": 155
    }, 
    {
      "source": 75, 
      "target": 163
    }, 
    {
      "source": 107, 
      "target": 44
    }, 
    {
      "source": 45, 
      "target": 108
    }, 
    {
      "source": 102, 
      "target": 108
    }, 
    {
      "source": 149, 
      "target": 108
    }, 
    {
      "source": 162, 
      "target": 75
    }, 
    {
      "source": 116, 
      "target": 75
    }, 
    {
      "source": 151, 
      "target": 5
    }, 
    {
      "source": 78, 
      "target": 5
    }, 
    {
      "source": 165, 
      "target": 128
    }, 
    {
      "source": 46, 
      "target": 116
    }, 
    {
      "source": 156, 
      "target": 116
    }, 
    {
      "source": 6, 
      "target": 151
    }, 
    {
      "source": 106, 
      "target": 46
    }, 
    {
      "source": 71, 
      "target": 6
    }, 
    {
      "source": 100, 
      "target": 106
    }, 
    {
      "source": 14, 
      "target": 71
    }, 
    {
      "source": 153, 
      "target": 14
    }, 
    {
      "source": 15, 
      "target": 153
    }, 
    {
      "source": 85, 
      "target": 100
    }, 
    {
      "source": 16, 
      "target": 15
    }, 
    {
      "source": 147, 
      "target": 15
    }, 
    {
      "source": 17, 
      "target": 147
    }, 
    {
      "source": 47, 
      "target": 147
    }, 
    {
      "source": 157, 
      "target": 17
    }, 
    {
      "source": 90, 
      "target": 17
    }, 
    {
      "source": 48, 
      "target": 17
    }, 
    {
      "source": 105, 
      "target": 17
    }, 
    {
      "source": 49, 
      "target": 157
    }, 
    {
      "source": 18, 
      "target": 90
    }, 
    {
      "source": 154, 
      "target": 90
    }, 
    {
      "source": 84, 
      "target": 18
    }, 
    {
      "source": 101, 
      "target": 18
    }, 
    {
      "source": 82, 
      "target": 154
    }, 
    {
      "source": 30, 
      "target": 84
    }, 
    {
      "source": 127, 
      "target": 81
    }, 
    {
      "source": 32, 
      "target": 81
    }, 
    {
      "source": 109, 
      "target": 81
    }, 
    {
      "source": 76, 
      "target": 81
    }, 
    {
      "source": 142, 
      "target": 81
    }, 
    {
      "source": 121, 
      "target": 81
    }, 
    {
      "source": 158, 
      "target": 81
    }, 
    {
      "source": 161, 
      "target": 49
    }, 
    {
      "source": 7, 
      "target": 30
    }, 
    {
      "source": 92, 
      "target": 30
    }, 
    {
      "source": 152, 
      "target": 30
    }, 
    {
      "source": 52, 
      "target": 30
    }, 
    {
      "source": 50, 
      "target": 101
    }, 
    {
      "source": 51, 
      "target": 161
    }, 
    {
      "source": 72, 
      "target": 7
    }, 
    {
      "source": 138, 
      "target": 92
    }, 
    {
      "source": 115, 
      "target": 92
    }, 
    {
      "source": 88, 
      "target": 152
    }, 
    {
      "source": 53, 
      "target": 52
    }, 
    {
      "source": 104, 
      "target": 95
    }, 
    {
      "source": 164, 
      "target": 95
    }, 
    {
      "source": 99, 
      "target": 95
    }, 
    {
      "source": 34, 
      "target": 142
    }, 
    {
      "source": 129, 
      "target": 142
    }, 
    {
      "source": 54, 
      "target": 53
    }, 
    {
      "source": 96, 
      "target": 137
    }, 
    {
      "source": 1, 
      "target": 134
    }, 
    {
      "source": 55, 
      "target": 134
    }, 
    {
      "source": 133, 
      "target": 1
    }, 
    {
      "source": 136, 
      "target": 55
    }, 
    {
      "source": 143, 
      "target": 133
    }, 
    {
      "source": 86, 
      "target": 133
    }, 
    {
      "source": 130, 
      "target": 133
    }, 
    {
      "source": 140, 
      "target": 129
    }, 
    {
      "source": 19, 
      "target": 88
    }, 
    {
      "source": 141, 
      "target": 88
    }, 
    {
      "source": 103, 
      "target": 140
    }, 
    {
      "source": 117, 
      "target": 140
    }, 
    {
      "source": 119, 
      "target": 19
    }, 
    {
      "source": 56, 
      "target": 141
    }, 
    {
      "source": 148, 
      "target": 141
    }, 
    {
      "source": 57, 
      "target": 119
    }, 
    {
      "source": 58, 
      "target": 119
    }, 
    {
      "source": 20, 
      "target": 119
    }, 
    {
      "source": 98, 
      "target": 119
    }, 
    {
      "source": 80, 
      "target": 119
    }, 
    {
      "source": 33, 
      "target": 119
    }, 
    {
      "source": 123, 
      "target": 57
    }, 
    {
      "source": 83, 
      "target": 121
    }, 
    {
      "source": 112, 
      "target": 20
    }, 
    {
      "source": 144, 
      "target": 59
    }, 
    {
      "source": 97, 
      "target": 117
    }, 
    {
      "source": 37, 
      "target": 117
    }, 
    {
      "source": 145, 
      "target": 60
    }, 
    {
      "source": 139, 
      "target": 86
    }, 
    {
      "source": 110, 
      "target": 98
    }, 
    {
      "source": 61, 
      "target": 139
    }, 
    {
      "source": 108, 
      "target": 83
    }, 
    {
      "source": 35, 
      "target": 83
    }, 
    {
      "source": 62, 
      "target": 130
    }, 
    {
      "source": 132, 
      "target": 130
    }, 
    {
      "source": 63, 
      "target": 110
    }, 
    {
      "source": 111, 
      "target": 63
    }, 
    {
      "source": 91, 
      "target": 80
    }, 
    {
      "source": 124, 
      "target": 80
    }, 
    {
      "source": 31, 
      "target": 35
    }, 
    {
      "source": 13, 
      "target": 35
    }, 
    {
      "source": 36, 
      "target": 35
    }, 
    {
      "source": 21, 
      "target": 33
    }, 
    {
      "source": 125, 
      "target": 33
    }, 
    {
      "source": 22, 
      "target": 21
    }, 
    {
      "source": 94, 
      "target": 125
    }, 
    {
      "source": 134, 
      "target": 97
    }, 
    {
      "source": 38, 
      "target": 97
    }, 
    {
      "source": 93, 
      "target": 22
    }, 
    {
      "source": 23, 
      "target": 22
    }, 
    {
      "source": 8, 
      "target": 94
    }, 
    {
      "source": 39, 
      "target": 36
    }, 
    {
      "source": 9, 
      "target": 124
    }, 
    {
      "source": 0, 
      "target": 124
    }, 
    {
      "source": 122, 
      "target": 9
    }, 
    {
      "source": 120, 
      "target": 0
    }, 
    {
      "source": 146, 
      "target": 135
    }, 
    {
      "source": 64, 
      "target": 135
    }, 
    {
      "source": 131, 
      "target": 64
    }, 
    {
      "source": 12, 
      "target": 120
    }, 
    {
      "source": 114, 
      "target": 23
    }, 
    {
      "source": 25, 
      "target": 114
    }, 
    {
      "source": 11, 
      "target": 113
    }, 
    {
      "source": 24, 
      "target": 113
    }, 
    {
      "source": 65, 
      "target": 113
    }, 
    {
      "source": 26, 
      "target": 24
    }, 
    {
      "source": 2, 
      "target": 158
    }, 
    {
      "source": 40, 
      "target": 158
    }, 
    {
      "source": 41, 
      "target": 39
    }, 
    {
      "source": 159, 
      "target": 40
    }, 
    {
      "source": 42, 
      "target": 159
    }
  ]
}